scrapyq/__init__.py
scrapyq/redis.py
scrapyq/spiderqueue.py
scrapyq-1.0.0.dist-info/METADATA
scrapyq-1.0.0.dist-info/WHEEL
scrapyq-1.0.0.dist-info/top_level.txt
scrapyq-1.0.0.dist-info/zip-safe
scrapyq-1.0.0.dist-info/RECORD
